reptar/__init__.py
reptar/_version.py
reptar/creating.py
reptar/descriptors.py
reptar/fragment.py
reptar/logger.py
reptar/periodic.py
reptar/reptar_file.py
reptar/sampling.py
reptar/save.py
reptar/utils.py
reptar/calculators/__init__.py
reptar/calculators/drivers.py
reptar/calculators/psi4_workers.py
reptar/calculators/xtb_workers.py
reptar/definitions/__init__.py
reptar/definitions/base.yaml
reptar/definitions/md.yaml
reptar/definitions/molprop.yaml
reptar/definitions/pes.yaml
reptar/definitions/qc.yaml
reptar/definitions/sampling.yaml
reptar/definitions/solv.yaml
reptar/definitions/xtb.yaml
reptar/extractors/__init__.py
reptar/extractors/ase_extractor.py
reptar/extractors/crest_extractor.py
reptar/extractors/extractor.py
reptar/extractors/orca_extractor.py
reptar/extractors/xtb_extractor.py
reptar/parsers/__init__.py
reptar/parsers/ase_parser.py
reptar/parsers/crest_parser.py
reptar/parsers/orca_parser.py
reptar/parsers/parser.py
reptar/parsers/xtb_parser.py
reptar/writers/__init__.py
reptar/writers/ase_db.py
reptar/writers/pdb.py
reptar/writers/schnetpack_db.py
reptar/writers/writing_utils.py
reptar/writers/xyz.py
reptar/writers/xyz_gap.py
reptar-0.1.0.data/scripts/reptar-write-xyz
reptar-0.1.0.dist-info/LICENSE
reptar-0.1.0.dist-info/METADATA
reptar-0.1.0.dist-info/WHEEL
reptar-0.1.0.dist-info/top_level.txt
reptar-0.1.0.dist-info/RECORD
