Metadata-Version: 2.1
Name: reptar
Version: 0.1.0
Summary: A tool for storing and analyzing manuscript-scale computational chemistry data
Author: Alex M. Maldonado
Author-email: aalexmmaldonado@gmail.com
License: MIT license
Classifier: Development Status :: 4 - Beta
Classifier: Intended Audience :: Science/Research
Classifier: License :: OSI Approved :: MIT License
Classifier: Natural Language :: English
Classifier: Programming Language :: Python :: 3
Classifier: Topic :: Scientific/Engineering
Classifier: Topic :: Scientific/Engineering :: Chemistry
Classifier: Topic :: System :: Archiving
Requires-Python: >=3.7
License-File: LICENSE
Requires-Dist: numpy
Requires-Dist: exdir (>=0.4.2)
Requires-Dist: cclib (>=1.7.0)
Requires-Dist: scipy
Requires-Dist: qcelemental (>=0.25.1)
Requires-Dist: pyyaml
Requires-Dist: ase
Requires-Dist: zarr
Requires-Dist: pytest
Requires-Dist: pytest-order
Requires-Dist: pytest-dependency
